bankkonto/__init__.py
bankkonto/__version__.py
bankkonto/account.py
bankkonto/clearing.py
bankkonto/exceptions.py
bankkonto/flask.py
bankkonto/luhn.py
bankkonto-1.0.1.dist-info/licenses/AUTHORS.md
bankkonto-1.0.1.dist-info/licenses/LICENSE
bankkonto-1.0.1.dist-info/METADATA
bankkonto-1.0.1.dist-info/WHEEL
bankkonto-1.0.1.dist-info/entry_points.txt
bankkonto-1.0.1.dist-info/top_level.txt
bankkonto-1.0.1.dist-info/RECORD
