Metadata-Version: 2.4
Name: bankkonto
Version: 1.0.1
Summary: Python validation library for Swedish bank account numbers
Author-email: Henrik Blidh <henrik.blidh@nedomkull.com>
License: MIT
Project-URL: homepage, https://github.com/hbldh/bankkonto
Keywords: Bank,Bank account,Swedish bank account,validation
Classifier: Development Status :: 4 - Beta
Classifier: License :: OSI Approved :: MIT License
Classifier: Operating System :: OS Independent
Classifier: Programming Language :: Python
Classifier: Programming Language :: Python :: 3
Classifier: Intended Audience :: Developers
Classifier: Intended Audience :: Financial and Insurance Industry
Classifier: Intended Audience :: Information Technology
Classifier: Intended Audience :: Telecommunications Industry
Classifier: Topic :: Office/Business :: Financial
License-File: LICENSE
License-File: AUTHORS.md
Dynamic: license-file
